data_collection_tool.py
honghu_data_collection-0.1.2.dist-info/METADATA
honghu_data_collection-0.1.2.dist-info/WHEEL
honghu_data_collection-0.1.2.dist-info/top_level.txt
honghu_data_collection-0.1.2.dist-info/RECORD
