Metadata-Version: 2.1
Name: honghu-data-collection
Version: 0.1.2
Summary: 红湖·数据汇聚管理平台PYTHON SDK
Author: xuzhaocai
Requires-Python: >=3.6
Requires-Dist: requests (>=2.25.1)
